{
  "$schema": "http://json-schema.org/draft-07/schema#",
  "title": "claim-cvc:Medical.code-v1",
  "$id": "http://identity.com/schemas/claim-cvc:Medical.code-v1",
  "type": "object",
  "properties": {
    "name": {
      "type": "string",
      "allOf": [
        {
          "$ref": "http://identity.com/schemas/cvc:Code:name"
        }
      ]
    },
    "code": {
      "type": "string",
      "allOf": [
        {
          "$ref": "http://identity.com/schemas/cvc:Code:code"
        }
      ]
    },
    "codeSystem": {
      "type": "string",
      "allOf": [
        {
          "$ref": "http://identity.com/schemas/cvc:Code:codeSystem"
        }
      ]
    },
    "codeSystemName": {
      "type": "string",
      "allOf": [
        {
          "$ref": "http://identity.com/schemas/cvc:Code:codeSystemName"
        }
      ]
    }
  },
  "required": ["name", "code"],
  "additionalProperties": false,
  "credentialItem": false
}
